gds3xtrude/__init__.py
gds3xtrude/blender.py
gds3xtrude/blender_extrusion_example.py
gds3xtrude/blender_test.py
gds3xtrude/builder.py
gds3xtrude/gds3xtrude.py
gds3xtrude/include.py
gds3xtrude/layer_operations.py
gds3xtrude/openscad.py
gds3xtrude/polygon_approx.py
gds3xtrude/types.py
gds3xtrude-0.0.8.data/scripts/gds3xtrude
gds3xtrude-0.0.8.dist-info/COPYING
gds3xtrude-0.0.8.dist-info/LICENSE
gds3xtrude-0.0.8.dist-info/METADATA
gds3xtrude-0.0.8.dist-info/WHEEL
gds3xtrude-0.0.8.dist-info/top_level.txt
gds3xtrude-0.0.8.dist-info/RECORD
