Metadata-Version: 2.1
Name: gds3xtrude
Version: 0.0.8
Summary: 3D GDS viewer based on OpenSCAD
Home-page: https://codeberg.org/tok/gds3xtrude
Author: T. Kramer
Author-email: code@tkramer.ch
License: AGPL
Keywords: gds openscad 3d viewer layout klayout
Platform: UNKNOWN
Classifier: License :: OSI Approved :: GNU Affero General Public License v3
Classifier: Development Status :: 3 - Alpha
Classifier: Topic :: Scientific/Engineering
Classifier: Topic :: Scientific/Engineering :: Visualization
Classifier: Topic :: Scientific/Engineering :: Electronic Design Automation (EDA)
Classifier: Programming Language :: Python :: 3
Requires-Dist: solidpython
Provides-Extra: standalone
Requires-Dist: klayout ; extra == 'standalone'
